share_links/__init__.py
share_links/__version__.py
share_links/admin.py
share_links/admin_utils.py
share_links/apps.py
share_links/cms_apps.py
share_links/conf.py
share_links/filters.py
share_links/forms.py
share_links/models.py
share_links/translation.py
share_links/urls.py
share_links/utils.py
share_links/views.py
share_links/apps/__init__.py
share_links/apps/admin/admin.py
share_links/apps/admin/apps.py
share_links/apps/share_links_comments/__init__.py
share_links/apps/share_links_comments/admin.py
share_links/apps/share_links_comments/apps.py
share_links/apps/share_links_comments/forms.py
share_links/apps/share_links_comments/models.py
share_links/apps/share_links_comments/locale/fr/LC_MESSAGES/django.mo
share_links/apps/share_links_comments/locale/fr/LC_MESSAGES/django.po
share_links/apps/share_links_comments/migrations/0001_initial.py
share_links/apps/share_links_comments/migrations/0002_alter_commentwithcaptcha_options_and_more.py
share_links/apps/share_links_comments/migrations/__init__.py
share_links/apps/share_links_comments/templates/comments/form.html
share_links/apps/share_links_comments/templates/comments/list.html
share_links/fixtures/default_categories_and_tags.json
share_links/locale/fr/LC_MESSAGES/django.mo
share_links/locale/fr/LC_MESSAGES/django.po
share_links/management/commands/add_missing_languages.py
share_links/management/commands/add_missing_titles.py
share_links/management/commands/check_online_status.py
share_links/migrations/0001_initial.py
share_links/migrations/0002_alter_link_file.py
share_links/migrations/0003_linktranslation_title.py
share_links/migrations/0004_link_online.py
share_links/migrations/0005_link_added_by.py
share_links/migrations/0006_delete_historylink_delete_historytag.py
share_links/migrations/0007_link_language.py
share_links/migrations/0008_collection_collectionlink_collectiontranslation_and_more.py
share_links/migrations/0009_link_allow_override_language_and_more.py
share_links-1.1.0.dist-info/licenses/LICENSE
share_links-1.1.0.dist-info/METADATA
share_links-1.1.0.dist-info/WHEEL
share_links-1.1.0.dist-info/top_level.txt
share_links-1.1.0.dist-info/RECORD
