Metadata-Version: 2.4
Name: share-links
Version: 1.1.0
Summary: Simple and efficient django app for storing, organizing, and sharing links.
Author-email: Corentin Bettiol <corentin@244466666.xyz>
License-Expression: WTFPL
Project-URL: Homepage, https://share-links.l3m.in/
Project-URL: Documentation, https://doc.share-links.l3m.in/
Project-URL: Source, https://gitlab.com/sodimel/share-links/
Project-URL: Issues, https://gitlab.com/sodimel/share-links/-/issues
Classifier: Programming Language :: Python :: 3
Classifier: Operating System :: OS Independent
Requires-Python: >=3.9
License-File: LICENSE
Requires-Dist: asgiref==3.*
Requires-Dist: Django==5.*
Requires-Dist: django-contrib-comments==2.*
Requires-Dist: django-markdownify==0.*
Requires-Dist: django-simple-math-captcha==2.*
Requires-Dist: django-parler==2.*
Requires-Dist: python-Levenshtein==0.27.*
Requires-Dist: django-filter==25.*
Provides-Extra: pdf
Requires-Dist: weasyprint==65.*; extra == "pdf"
Provides-Extra: dev
Requires-Dist: ruff; extra == "dev"
Requires-Dist: pre-commit; extra == "dev"
Requires-Dist: pytest-django; extra == "dev"
Requires-Dist: pytest-cov; extra == "dev"
Requires-Dist: django-debug-toolbar; extra == "dev"
Requires-Dist: bump-my-version; extra == "dev"
Requires-Dist: mkdocs; extra == "dev"
Requires-Dist: pymdown-extensions; extra == "dev"
Requires-Dist: git-cliff; extra == "dev"
Requires-Dist: twine; extra == "dev"
Dynamic: license-file
